<!-- This is a mockup plugin with original field names and such -->
<!-- Made by Zedd lol -->
<plugin>
	<_field_int64_integer name="vtable space*~!" />
	<_field_struct name="internal struct" srcguid="151d0146-479c-181f-3970-ec869043bc33">
		<_field_long_integer name="global tag ID!" />
		<_field_pad name="local tag handle!~" length="4" />
	</_field_struct>
	<_field_tag_reference_64 name="navpoint tag" validtags="navp" />
	<_field_long_flags name="navpoint flags">
		<item Name="Draw clamped to gutter if offscreen" />
	</_field_long_flags>
	<_field_explanation name="center sprite bg" />
	<_field_struct name="center sprite bg" srcguid="3767749b-47d1-71d1-038c-8da2c502cd2a">
		<_field_real_argb_color name="color" />
		<_field_long_enum name="sequence index">
			<item Name="TacticalObjective" />
			<item Name="SubObjective" />
			<item Name="MainObjective" />
			<item Name="SupplyCache" />
			<item Name="MoveToIndicator" />
			<item Name="ChatterIndicator" />
			<item Name="AttackCommandFg" />
			<item Name="ReviveFg" />
			<item Name="ReviveBg" />
			<item Name="BleedoutTimerStroke" />
			<item Name="ReviveCommand" />
			<item Name="ReviveHelpPulse" />
			<item Name="WzBossFg" />
			<item Name="WzBossBg" />
			<item Name="WzReqFg" />
			<item Name="WzHomeBaseFg" />
			<item Name="AttackFg" />
			<item Name="DefendFg" />
			<item Name="CircleBg" />
			<item Name="DiamondBg" />
			<item Name="SquareBg" />
			<item Name="HexBg" />
			<item Name="CircleStroke" />
			<item Name="DiamondStroke" />
			<item Name="SquareStroke" />
			<item Name="HexStroke" />
			<item Name="ExclamationFg" />
			<item Name="DeadIndicator" />
			<item Name="SpeakingIndicator" />
			<item Name="WeaponPadFg" />
			<item Name="CubeFg" />
			<item Name="FlagFg" />
			<item Name="LetterAFg" />
			<item Name="LetterBFg" />
			<item Name="LetterCFg" />
			<item Name="BombFg" />
			<item Name="CrownFg" />
			<item Name="SmallOffscreenArrow" />
			<item Name="FriendlyArrow" />
			<item Name="EnemyArrow" />
			<item Name="SeekIndicator" />
			<item Name="LockOnIndicator" />
			<item Name="ReqBg" />
			<item Name="Num0Fg" />
			<item Name="Num1Fg" />
			<item Name="Num2Fg" />
			<item Name="Num3Fg" />
			<item Name="Num4Fg" />
			<item Name="Num5Fg" />
			<item Name="Num6Fg" />
			<item Name="Num7Fg" />
			<item Name="Num8Fg" />
			<item Name="Num9Fg" />
			<item Name="Flipbook1" />
			<item Name="Flipbook2" />
			<item Name="Flipbook3" />
			<item Name="Flipbook4" />
			<item Name="Flipbook5" />
			<item Name="Flipbook6" />
			<item Name="Flipbook7" />
			<item Name="Flipbook8" />
			<item Name="Flipbook9" />
			<item Name="Flipbook10" />
			<item Name="Flipbook11" />
			<item Name="Flipbook12" />
			<item Name="Flipbook13" />
			<item Name="Flipbook14" />
			<item Name="Flipbook15" />
			<item Name="Flipbook16" />
			<item Name="Flipbook17" />
			<item Name="Flipbook18" />
			<item Name="Flipbook19" />
			<item Name="Flipbook20" />
			<item Name="Flipbook21" />
			<item Name="Flipbook22" />
			<item Name="Flipbook23" />
			<item Name="Flipbook24" />
		</_field_long_enum>
		<_field_long_enum name="flipbook loop type">
			<item Name="LoopForward" />
			<item Name="LoopReversed" />
			<item Name="LoopForwardThenReversed" />
			<item Name="PlayOnceThenHold" />
			<item Name="PlayOnceReversedThenHold" />
		</_field_long_enum>
		<_field_real name="flipbook delay before looping" />
		<_field_long_flags name="drawing flags">
			<item Name="Draw when onscreen" />
			<item Name="Draw when offscreen" />
			<item Name="Draw when under reticule" />
		</_field_long_flags>
	</_field_struct>
	<_field_explanation name="center sprite fg" />
	<_field_struct name="center sprite fg" srcguid="3767749b-47d1-71d1-038c-8da2c502cd2a">
		<_field_real_argb_color name="color" />
		<_field_long_enum name="sequence index">
			<item Name="TacticalObjective" />
			<item Name="SubObjective" />
			<item Name="MainObjective" />
			<item Name="SupplyCache" />
			<item Name="MoveToIndicator" />
			<item Name="ChatterIndicator" />
			<item Name="AttackCommandFg" />
			<item Name="ReviveFg" />
			<item Name="ReviveBg" />
			<item Name="BleedoutTimerStroke" />
			<item Name="ReviveCommand" />
			<item Name="ReviveHelpPulse" />
			<item Name="WzBossFg" />
			<item Name="WzBossBg" />
			<item Name="WzReqFg" />
			<item Name="WzHomeBaseFg" />
			<item Name="AttackFg" />
			<item Name="DefendFg" />
			<item Name="CircleBg" />
			<item Name="DiamondBg" />
			<item Name="SquareBg" />
			<item Name="HexBg" />
			<item Name="CircleStroke" />
			<item Name="DiamondStroke" />
			<item Name="SquareStroke" />
			<item Name="HexStroke" />
			<item Name="ExclamationFg" />
			<item Name="DeadIndicator" />
			<item Name="SpeakingIndicator" />
			<item Name="WeaponPadFg" />
			<item Name="CubeFg" />
			<item Name="FlagFg" />
			<item Name="LetterAFg" />
			<item Name="LetterBFg" />
			<item Name="LetterCFg" />
			<item Name="BombFg" />
			<item Name="CrownFg" />
			<item Name="SmallOffscreenArrow" />
			<item Name="FriendlyArrow" />
			<item Name="EnemyArrow" />
			<item Name="SeekIndicator" />
			<item Name="LockOnIndicator" />
			<item Name="ReqBg" />
			<item Name="Num0Fg" />
			<item Name="Num1Fg" />
			<item Name="Num2Fg" />
			<item Name="Num3Fg" />
			<item Name="Num4Fg" />
			<item Name="Num5Fg" />
			<item Name="Num6Fg" />
			<item Name="Num7Fg" />
			<item Name="Num8Fg" />
			<item Name="Num9Fg" />
			<item Name="Flipbook1" />
			<item Name="Flipbook2" />
			<item Name="Flipbook3" />
			<item Name="Flipbook4" />
			<item Name="Flipbook5" />
			<item Name="Flipbook6" />
			<item Name="Flipbook7" />
			<item Name="Flipbook8" />
			<item Name="Flipbook9" />
			<item Name="Flipbook10" />
			<item Name="Flipbook11" />
			<item Name="Flipbook12" />
			<item Name="Flipbook13" />
			<item Name="Flipbook14" />
			<item Name="Flipbook15" />
			<item Name="Flipbook16" />
			<item Name="Flipbook17" />
			<item Name="Flipbook18" />
			<item Name="Flipbook19" />
			<item Name="Flipbook20" />
			<item Name="Flipbook21" />
			<item Name="Flipbook22" />
			<item Name="Flipbook23" />
			<item Name="Flipbook24" />
		</_field_long_enum>
		<_field_long_enum name="flipbook loop type">
			<item Name="LoopForward" />
			<item Name="LoopReversed" />
			<item Name="LoopForwardThenReversed" />
			<item Name="PlayOnceThenHold" />
			<item Name="PlayOnceReversedThenHold" />
		</_field_long_enum>
		<_field_real name="flipbook delay before looping" />
		<_field_long_flags name="drawing flags">
			<item Name="Draw when onscreen" />
			<item Name="Draw when offscreen" />
			<item Name="Draw when under reticule" />
		</_field_long_flags>
	</_field_struct>
	<_field_explanation name="center radial progress bar" />
	<_field_struct name="center radial progress bar" srcguid="3e47d156-424b-6d2d-9ce0-40b9a838b915">
		<_field_real_argb_color name="left color" />
		<_field_real_argb_color name="right color" />
		<_field_long_enum name="sequenceIndex">
			<item Name="TacticalObjective" />
			<item Name="SubObjective" />
			<item Name="MainObjective" />
			<item Name="SupplyCache" />
			<item Name="MoveToIndicator" />
			<item Name="ChatterIndicator" />
			<item Name="AttackCommandFg" />
			<item Name="ReviveFg" />
			<item Name="ReviveBg" />
			<item Name="BleedoutTimerStroke" />
			<item Name="ReviveCommand" />
			<item Name="ReviveHelpPulse" />
			<item Name="WzBossFg" />
			<item Name="WzBossBg" />
			<item Name="WzReqFg" />
			<item Name="WzHomeBaseFg" />
			<item Name="AttackFg" />
			<item Name="DefendFg" />
			<item Name="CircleBg" />
			<item Name="DiamondBg" />
			<item Name="SquareBg" />
			<item Name="HexBg" />
			<item Name="CircleStroke" />
			<item Name="DiamondStroke" />
			<item Name="SquareStroke" />
			<item Name="HexStroke" />
			<item Name="ExclamationFg" />
			<item Name="DeadIndicator" />
			<item Name="SpeakingIndicator" />
			<item Name="WeaponPadFg" />
			<item Name="CubeFg" />
			<item Name="FlagFg" />
			<item Name="LetterAFg" />
			<item Name="LetterBFg" />
			<item Name="LetterCFg" />
			<item Name="BombFg" />
			<item Name="CrownFg" />
			<item Name="SmallOffscreenArrow" />
			<item Name="FriendlyArrow" />
			<item Name="EnemyArrow" />
			<item Name="SeekIndicator" />
			<item Name="LockOnIndicator" />
			<item Name="ReqBg" />
			<item Name="Num0Fg" />
			<item Name="Num1Fg" />
			<item Name="Num2Fg" />
			<item Name="Num3Fg" />
			<item Name="Num4Fg" />
			<item Name="Num5Fg" />
			<item Name="Num6Fg" />
			<item Name="Num7Fg" />
			<item Name="Num8Fg" />
			<item Name="Num9Fg" />
		</_field_long_enum>
		<_field_real name="fraction" />
		<_field_long_flags name="drawing flags">
			<item Name="Draw when onscreen" />
			<item Name="Draw when offscreen" />
			<item Name="Draw when under reticule" />
		</_field_long_flags>
	</_field_struct>
	<_field_explanation name="top sprite" />
	<_field_struct name="top sprite" srcguid="3767749b-47d1-71d1-038c-8da2c502cd2a">
		<_field_real_argb_color name="color" />
		<_field_long_enum name="sequence index">
			<item Name="TacticalObjective" />
			<item Name="SubObjective" />
			<item Name="MainObjective" />
			<item Name="SupplyCache" />
			<item Name="MoveToIndicator" />
			<item Name="ChatterIndicator" />
			<item Name="AttackCommandFg" />
			<item Name="ReviveFg" />
			<item Name="ReviveBg" />
			<item Name="BleedoutTimerStroke" />
			<item Name="ReviveCommand" />
			<item Name="ReviveHelpPulse" />
			<item Name="WzBossFg" />
			<item Name="WzBossBg" />
			<item Name="WzReqFg" />
			<item Name="WzHomeBaseFg" />
			<item Name="AttackFg" />
			<item Name="DefendFg" />
			<item Name="CircleBg" />
			<item Name="DiamondBg" />
			<item Name="SquareBg" />
			<item Name="HexBg" />
			<item Name="CircleStroke" />
			<item Name="DiamondStroke" />
			<item Name="SquareStroke" />
			<item Name="HexStroke" />
			<item Name="ExclamationFg" />
			<item Name="DeadIndicator" />
			<item Name="SpeakingIndicator" />
			<item Name="WeaponPadFg" />
			<item Name="CubeFg" />
			<item Name="FlagFg" />
			<item Name="LetterAFg" />
			<item Name="LetterBFg" />
			<item Name="LetterCFg" />
			<item Name="BombFg" />
			<item Name="CrownFg" />
			<item Name="SmallOffscreenArrow" />
			<item Name="FriendlyArrow" />
			<item Name="EnemyArrow" />
			<item Name="SeekIndicator" />
			<item Name="LockOnIndicator" />
			<item Name="ReqBg" />
			<item Name="Num0Fg" />
			<item Name="Num1Fg" />
			<item Name="Num2Fg" />
			<item Name="Num3Fg" />
			<item Name="Num4Fg" />
			<item Name="Num5Fg" />
			<item Name="Num6Fg" />
			<item Name="Num7Fg" />
			<item Name="Num8Fg" />
			<item Name="Num9Fg" />
			<item Name="Flipbook1" />
			<item Name="Flipbook2" />
			<item Name="Flipbook3" />
			<item Name="Flipbook4" />
			<item Name="Flipbook5" />
			<item Name="Flipbook6" />
			<item Name="Flipbook7" />
			<item Name="Flipbook8" />
			<item Name="Flipbook9" />
			<item Name="Flipbook10" />
			<item Name="Flipbook11" />
			<item Name="Flipbook12" />
			<item Name="Flipbook13" />
			<item Name="Flipbook14" />
			<item Name="Flipbook15" />
			<item Name="Flipbook16" />
			<item Name="Flipbook17" />
			<item Name="Flipbook18" />
			<item Name="Flipbook19" />
			<item Name="Flipbook20" />
			<item Name="Flipbook21" />
			<item Name="Flipbook22" />
			<item Name="Flipbook23" />
			<item Name="Flipbook24" />
		</_field_long_enum>
		<_field_long_enum name="flipbook loop type">
			<item Name="LoopForward" />
			<item Name="LoopReversed" />
			<item Name="LoopForwardThenReversed" />
			<item Name="PlayOnceThenHold" />
			<item Name="PlayOnceReversedThenHold" />
		</_field_long_enum>
		<_field_real name="flipbook delay before looping" />
		<_field_long_flags name="drawing flags">
			<item Name="Draw when onscreen" />
			<item Name="Draw when offscreen" />
			<item Name="Draw when under reticule" />
		</_field_long_flags>
	</_field_struct>
	<_field_explanation name="top label" />
	<_field_struct name="top label" srcguid="35933425-4d02-a80b-136e-60bcacce1553">
		<_field_real_argb_color name="color" />
		<_field_string_id name="label" />
		<_field_long_flags name="drawing flags">
			<item Name="Draw when onscreen" />
			<item Name="Draw when offscreen" />
			<item Name="Draw when under reticule" />
		</_field_long_flags>
	</_field_struct>
	<_field_explanation name="right progress bar" />
	<_field_struct name="right progress bar" srcguid="6a211e5b-4f90-6de5-0192-dcb3c8afa0e8">
		<_field_real_argb_color name="left color" />
		<_field_real_argb_color name="right color" />
		<_field_real name="fraction" />
		<_field_long_flags name="drawing flags">
			<item Name="Draw when onscreen" />
			<item Name="Draw when offscreen" />
			<item Name="Draw when under reticule" />
		</_field_long_flags>
	</_field_struct>
	<_field_explanation name="right progress bar 2" />
	<_field_struct name="right progress bar 2" srcguid="6a211e5b-4f90-6de5-0192-dcb3c8afa0e8">
		<_field_real_argb_color name="left color" />
		<_field_real_argb_color name="right color" />
		<_field_real name="fraction" />
		<_field_long_flags name="drawing flags">
			<item Name="Draw when onscreen" />
			<item Name="Draw when offscreen" />
			<item Name="Draw when under reticule" />
		</_field_long_flags>
	</_field_struct>
	<_field_explanation name="right label" />
	<_field_struct name="right label" srcguid="35933425-4d02-a80b-136e-60bcacce1553">
		<_field_real_argb_color name="color" />
		<_field_string_id name="label" />
		<_field_long_flags name="drawing flags">
			<item Name="Draw when onscreen" />
			<item Name="Draw when offscreen" />
			<item Name="Draw when under reticule" />
		</_field_long_flags>
	</_field_struct>
	<_field_explanation name="right timer" />
	<_field_struct name="right timer" srcguid="185e7090-4b24-9d37-95f1-b0b58bb4fd35">
		<_field_real_argb_color name="color" />
		<_field_long_enum name="number format">
			<item Name="Timer" />
			<item Name="Distance" />
		</_field_long_enum>
		<_field_real name="number" />
		<_field_long_flags name="drawing flags">
			<item Name="Draw when onscreen" />
			<item Name="Draw when offscreen" />
			<item Name="Draw when under reticule" />
		</_field_long_flags>
	</_field_struct>
	<_field_explanation name="left timer" />
	<_field_struct name="left timer" srcguid="185e7090-4b24-9d37-95f1-b0b58bb4fd35">
		<_field_real_argb_color name="color" />
		<_field_long_enum name="number format">
			<item Name="Timer" />
			<item Name="Distance" />
		</_field_long_enum>
		<_field_real name="number" />
		<_field_long_flags name="drawing flags">
			<item Name="Draw when onscreen" />
			<item Name="Draw when offscreen" />
			<item Name="Draw when under reticule" />
		</_field_long_flags>
	</_field_struct>
	<_field_explanation name="yaw sprite" />
	<_field_struct name="yaw sprite" srcguid="345fe9f9-4b0c-b08d-9274-dea49b48ccb0">
		<_field_real_argb_color name="color" />
		<_field_long_enum name="sequence index">
			<item Name="TacticalObjective" />
			<item Name="SubObjective" />
			<item Name="MainObjective" />
			<item Name="SupplyCache" />
			<item Name="MoveToIndicator" />
			<item Name="ChatterIndicator" />
			<item Name="AttackCommandFg" />
			<item Name="ReviveFg" />
			<item Name="ReviveBg" />
			<item Name="BleedoutTimerStroke" />
			<item Name="ReviveCommand" />
			<item Name="ReviveHelpPulse" />
			<item Name="WzBossFg" />
			<item Name="WzBossBg" />
			<item Name="WzReqFg" />
			<item Name="WzHomeBaseFg" />
			<item Name="AttackFg" />
			<item Name="DefendFg" />
			<item Name="CircleBg" />
			<item Name="DiamondBg" />
			<item Name="SquareBg" />
			<item Name="HexBg" />
			<item Name="CircleStroke" />
			<item Name="DiamondStroke" />
			<item Name="SquareStroke" />
			<item Name="HexStroke" />
			<item Name="ExclamationFg" />
			<item Name="DeadIndicator" />
			<item Name="SpeakingIndicator" />
			<item Name="WeaponPadFg" />
			<item Name="CubeFg" />
			<item Name="FlagFg" />
			<item Name="LetterAFg" />
			<item Name="LetterBFg" />
			<item Name="LetterCFg" />
			<item Name="BombFg" />
			<item Name="CrownFg" />
			<item Name="SmallOffscreenArrow" />
			<item Name="FriendlyArrow" />
			<item Name="EnemyArrow" />
			<item Name="SeekIndicator" />
			<item Name="LockOnIndicator" />
			<item Name="ReqBg" />
			<item Name="Num0Fg" />
			<item Name="Num1Fg" />
			<item Name="Num2Fg" />
			<item Name="Num3Fg" />
			<item Name="Num4Fg" />
			<item Name="Num5Fg" />
			<item Name="Num6Fg" />
			<item Name="Num7Fg" />
			<item Name="Num8Fg" />
			<item Name="Num9Fg" />
		</_field_long_enum>
		<_field_long_flags name="drawing flags">
			<item Name="Draw when onscreen" />
			<item Name="Draw when offscreen" />
			<item Name="Draw when under reticule" />
		</_field_long_flags>
	</_field_struct>
	<_field_explanation name="animation" />
	<_field_struct name="animation" srcguid="d7a914fb-4bb3-0d3f-1307-77a66d020d41">
		<_field_long_enum name="animation type">
			<item Name="PlayerFiring" />
			<item Name="PlayerDamaged" />
			<item Name="ReviveIdle" />
			<item Name="RevivePulsing" />
			<item Name="Flashing" />
			<item Name="HomeBaseVulnerableAlternatingIcon" />
			<item Name="FlashTimer" />
			<item Name="Animation8" />
			<item Name="Animation9" />
			<item Name="Animation10" />
			<item Name="Animation11" />
			<item Name="Animation12" />
			<item Name="Animation13" />
			<item Name="Animation14" />
			<item Name="Animation15" />
			<item Name="Animation16" />
			<item Name="Animation17" />
			<item Name="Animation18" />
			<item Name="Animation19" />
			<item Name="Animation20" />
			<item Name="Animation21" />
			<item Name="Animation22" />
			<item Name="Animation23" />
			<item Name="Animation24" />
			<item Name="Animation25" />
			<item Name="Animation26" />
			<item Name="Animation27" />
			<item Name="Animation28" />
			<item Name="Animation29" />
			<item Name="Animation30" />
			<item Name="Animation31" />
			<item Name="Animation32" />
		</_field_long_enum>
		<_field_long_flags name="drawing flags">
			<item Name="Draw when onscreen" />
			<item Name="Draw when offscreen" />
			<item Name="Draw when under reticule" />
		</_field_long_flags>
	</_field_struct>
</plugin>